microcosm_postgres/__init__.py
microcosm_postgres/cloning.py
microcosm_postgres/constants.py
microcosm_postgres/context.py
microcosm_postgres/createall.py
microcosm_postgres/dag.py
microcosm_postgres/diff.py
microcosm_postgres/errors.py
microcosm_postgres/health.py
microcosm_postgres/identifiers.py
microcosm_postgres/metrics.py
microcosm_postgres/migrate.py
microcosm_postgres/models.py
microcosm_postgres/operations.py
microcosm_postgres/sharded_subgraph.py
microcosm_postgres/shards.py
microcosm_postgres/store.py
microcosm_postgres/toposort.py
microcosm_postgres/types.py
microcosm_postgres/encryption/__init__.py
microcosm_postgres/encryption/constants.py
microcosm_postgres/encryption/encryptor.py
microcosm_postgres/encryption/factories.py
microcosm_postgres/encryption/models.py
microcosm_postgres/encryption/providers.py
microcosm_postgres/encryption/registry.py
microcosm_postgres/encryption/store.py
microcosm_postgres/encryption/v2/__init__.py
microcosm_postgres/encryption/v2/beacons.py
microcosm_postgres/encryption/v2/column.py
microcosm_postgres/encryption/v2/contexts.py
microcosm_postgres/encryption/v2/encoders.py
microcosm_postgres/encryption/v2/encryptors.py
microcosm_postgres/encryption/v2/errors.py
microcosm_postgres/encryption/v2/utils.py
microcosm_postgres/encryption/v2/reencryption/__init__.py
microcosm_postgres/encryption/v2/reencryption/cli.py
microcosm_postgres/encryption/v2/reencryption/stats.py
microcosm_postgres/encryption/v2/reencryption/utils.py
microcosm_postgres/factories/__init__.py
microcosm_postgres/factories/engine.py
microcosm_postgres/factories/engine_routing_strategy.py
microcosm_postgres/factories/sessionmaker.py
microcosm_postgres/factories/sessionmakers.py
microcosm_postgres/factories/shards.py
microcosm_postgres/temporary/__init__.py
microcosm_postgres/temporary/context.py
microcosm_postgres/temporary/copy.py
microcosm_postgres/temporary/factories.py
microcosm_postgres/temporary/methods.py
microcosm_postgres-4.0.0.dist-info/LICENSE
microcosm_postgres-4.0.0.dist-info/METADATA
microcosm_postgres-4.0.0.dist-info/WHEEL
microcosm_postgres-4.0.0.dist-info/entry_points.txt
microcosm_postgres-4.0.0.dist-info/top_level.txt
microcosm_postgres-4.0.0.dist-info/RECORD
